_pine.py
pine-0.9.data/scripts/pine
pine-0.9.dist-info/DESCRIPTION.rst
pine-0.9.dist-info/LICENSE.txt
pine-0.9.dist-info/METADATA
pine-0.9.dist-info/RECORD
pine-0.9.dist-info/WHEEL
pine-0.9.dist-info/metadata.json
pine-0.9.dist-info/top_level.txt
