Metadata-Version: 2.0
Name: pine
Version: 0.9
Summary: A benchmark utility to make requests to a REST API.
Home-page: http://pine.readthedocs.io/en/latest/
Author: Brian Curtin
Author-email: brian@python.org
License: Apache 2
Keywords: benchmarks,testing
Platform: UNKNOWN
Classifier: Development Status :: 3 - Alpha
Classifier: Intended Audience :: Developers
Classifier: License :: OSI Approved :: Apache Software License
Classifier: Operating System :: OS Independent
Classifier: Programming Language :: Python
Classifier: Programming Language :: Python :: 3
Classifier: Programming Language :: Python :: 3.6
Classifier: Programming Language :: Python :: 3.7
Classifier: Programming Language :: Python :: Implementation :: CPython
Classifier: Topic :: Software Development :: Libraries :: Python Modules
Requires-Dist: aiohttp (>=3.0)
Requires-Dist: certifi (>=2018.1.18)
Requires-Dist: dataclasses (>=0.5); python_version < "3.7"
Requires-Dist: pyyaml (>=3.12); python_version == "3.6"
